README.md
setup.py
./poetry_setup/templates/MANIFEST.in
./poetry_setup/templates/requirements.txt.j2
./poetry_setup/templates/setup.cfg.j2
./poetry_setup/templates/setup.py.j2
poetry_setup/__init__.py
poetry_setup/__main__.py
poetry_setup/core.py
poetry_setup.egg-info/PKG-INFO
poetry_setup.egg-info/SOURCES.txt
poetry_setup.egg-info/dependency_links.txt
poetry_setup.egg-info/entry_points.txt
poetry_setup.egg-info/requires.txt
poetry_setup.egg-info/top_level.txt
poetry_setup/templates/MANIFEST.in
poetry_setup/templates/requirements.txt.j2
poetry_setup/templates/setup.cfg.j2
poetry_setup/templates/setup.py.j2