Metadata-Version: 2.1
Name: poetry-setup
Version: 0.3.6
Summary: make setup.py (setutools) from pyproject.toml (poetry)
Home-page: https://github.com/orsinium/poetry-setup
Author: Gram Orsinium
Author-email: master_fess@mail.ru
License: UNKNOWN
Project-URL: homepage, https://github.com/orsinium/poetry-setup
Keywords: packaging dependency poetry setuptools pip
Platform: UNKNOWN
Classifier: Development Status :: 4 - Beta
Classifier: Environment :: Console
Classifier: License :: OSI Approved :: Apache Software License
Classifier: Programming Language :: Python :: 3
Classifier: Programming Language :: Python :: 3.4
Classifier: Programming Language :: Python :: 3.5
Classifier: Programming Language :: Python :: 3.6
Classifier: Programming Language :: Python :: 3.7
Classifier: Topic :: Software Development :: Build Tools
Classifier: Topic :: Software Development :: Libraries :: Python Modules
